etl/__about__.py
etl/__init__.py
etl/constants.py
etl/logger.py
etl/database/__init__.py
etl/database/connector.py
etl/database/differentiator.py
etl/database/extra_column_exception.py
etl/database/loader.py
etl/database/mssql_loader.py
etl/database/mysql_loader.py
etl/database/readme.md
etl/database/sql_dialects.py
etl/database/unified_loader.py
etl/database/utils.py
etl/database/validator.py
etl/dataframe/__init__.py
etl/dataframe/analyzer.py
etl/dataframe/cleaner.py
etl/dataframe/parser.py
etl/dataframe/readme.md
etl/dataframe/polars/__init__.py
etl/dataframe/polars/cleaner.py
etl/dataframe/polars/parser.py
etl/dataframe/spark/__init__.py
etl/dataframe/spark/cleaner.py
etl/query/__init__.py
etl/query/creator.py
etl/query/mssql_updater.py
etl/query/readme.md
etl_utilities-1.1.9.dist-info/METADATA
etl_utilities-1.1.9.dist-info/WHEEL
etl_utilities-1.1.9.dist-info/licenses/LICENSE
etl_utilities-1.1.9.dist-info/RECORD
