Metadata-Version: 2.4
Name: etl_utilities
Version: 1.1.9
Summary: This repository provides a collection of utility functions and classes for data cleaning, SQL query generation, and data analysis. The code is written in Python and uses libraries such as `pandas`, `numpy`, and `dateutil`.
Project-URL: Documentation, https://github.com/magicjedi90/etl_utilities#readme
Project-URL: Issues, https://github.com/magicjedi90/etl_utilities/issues
Project-URL: Source, https://github.com/magicjedi90/etl_utilities
Author-email: Jesse <magicjedi90@aim.com>
License-Expression: MIT
License-File: LICENSE
Keywords: cleaning,database,dataframe,etl,etl-utilities,pandas,spark,utilities
Classifier: Development Status :: 4 - Beta
Classifier: Programming Language :: Python
Classifier: Programming Language :: Python :: 3.8
Classifier: Programming Language :: Python :: 3.9
Classifier: Programming Language :: Python :: 3.10
Classifier: Programming Language :: Python :: 3.11
Classifier: Programming Language :: Python :: 3.12
Classifier: Programming Language :: Python :: 3.13
Classifier: Programming Language :: Python :: Implementation :: CPython
Classifier: Programming Language :: Python :: Implementation :: PyPy
Requires-Python: >=3.8
Requires-Dist: numpy
Requires-Dist: pandas
Requires-Dist: polars
Requires-Dist: psycopg2-binary
Requires-Dist: pyspark
Requires-Dist: pytest>=8.3.5
Requires-Dist: python-dateutil
Requires-Dist: rich
Requires-Dist: sqlalchemy
